LICENSE
MANIFEST.in
README.md
pyproject.toml
requirements-dev.txt
requirements-docs.txt
requirements-optional.txt
requirements-test.txt
requirements.txt
setup.cfg
setup.py
docs/.buildinfo
docs/.nojekyll
docs/genindex.html
docs/index.html
docs/objects.inv
docs/py-modindex.html
docs/search.html
docs/searchindex.js
docs/_images/quickstart_example.png
docs/_images/tutorial_algorithm_explained_14_1.png
docs/_images/tutorial_algorithm_explained_16_0.png
docs/_images/tutorial_algorithm_explained_18_0.png
docs/_images/tutorial_algorithm_explained_20_0.png
docs/_images/tutorial_algorithm_explained_25_0.png
docs/_images/tutorial_algorithm_explained_30_1.png
docs/_images/tutorial_algorithm_explained_37_0.png
docs/_images/tutorial_algorithm_explained_41_0.png
docs/_images/tutorial_algorithm_explained_42_0.png
docs/_images/tutorial_algorithm_explained_45_1.png
docs/_images/tutorial_algorithm_explained_49_0.png
docs/_images/tutorial_basic_usage_25_0.png
docs/_images/tutorial_hierarchical_clustering_basics_16_0.png
docs/_images/tutorial_hierarchical_clustering_basics_20_1.png
docs/_images/tutorial_hierarchical_clustering_basics_23_0.png
docs/_images/tutorial_hierarchical_clustering_basics_33_0.png
docs/_images/tutorial_hierarchical_clustering_basics_36_0.png
docs/_images/tutorial_hierarchical_clustering_basics_38_0.png
docs/_images/tutorial_hierarchical_clustering_basics_40_0.png
docs/_images/tutorial_hierarchical_clustering_basics_42_0.png
docs/_images/tutorial_hierarchical_clustering_basics_46_0.png
docs/_images/tutorial_hierarchical_clustering_basics_59_0.png
docs/_images/tutorial_hierarchical_clustering_basics_61_1.png
docs/_images/tutorial_hierarchical_clustering_basics_63_1.png
docs/_images/tutorial_hierarchical_clustering_basics_65_0.png
docs/_images/tutorial_hierarchical_clustering_basics_68_1.png
docs/_images/tutorial_hierarchical_clustering_basics_69_0.png
docs/_images/tutorial_hierarchical_clustering_basics_76_1.png
docs/_images/tutorial_md_example_18_0.png
src/commonnn_clustering.egg-info/PKG-INFO
src/commonnn_clustering.egg-info/SOURCES.txt
src/commonnn_clustering.egg-info/dependency_links.txt
src/commonnn_clustering.egg-info/not-zip-safe
src/commonnn_clustering.egg-info/requires.txt
src/commonnn_clustering.egg-info/top_level.txt