Metadata-Version: 2.4
Name: commonnn-clustering
Version: 0.0.4
Summary: A Python package for common-nearest-neighbours clustering
Home-page: https://github.com/bkellerlab/CommonNNClustering
Author: Jan-Oliver Joswig
Author-email: jan.joswig@fu-berlin.de
Keywords: density-based clustering
Classifier: Development Status :: 3 - Alpha
Classifier: Programming Language :: Python :: 3
Classifier: Programming Language :: Python :: 3.6
Classifier: Programming Language :: Python :: 3.7
Classifier: Programming Language :: Python :: 3.8
Classifier: Programming Language :: Python :: 3.9
Classifier: Programming Language :: Python :: 3.10
Classifier: License :: OSI Approved :: MIT License
Classifier: Operating System :: OS Independent
License-File: LICENSE
Requires-Dist: loguru
Requires-Dist: numpy
Provides-Extra: optional
Requires-Dist: matplotlib; extra == "optional"
Requires-Dist: networkx; extra == "optional"
Requires-Dist: pandas; extra == "optional"
Requires-Dist: scikit-learn; extra == "optional"
Requires-Dist: scipy; extra == "optional"
Provides-Extra: dev
Requires-Dist: cython>=0.29; extra == "dev"
Requires-Dist: bump2version; extra == "dev"
Requires-Dist: anybadge; extra == "dev"
Provides-Extra: docs
Requires-Dist: ipython; extra == "docs"
Requires-Dist: nbsphinx; extra == "docs"
Requires-Dist: rstcheck; extra == "docs"
Requires-Dist: sphinx; extra == "docs"
Requires-Dist: sphinxcontrib-napoleon; extra == "docs"
Provides-Extra: test
Requires-Dist: coverage; extra == "test"
Requires-Dist: coveralls; extra == "test"
Requires-Dist: flake8; extra == "test"
Requires-Dist: pytest; extra == "test"
Requires-Dist: pytest-mock; extra == "test"
Requires-Dist: pytest-raises; extra == "test"
Requires-Dist: pytest-regressions; extra == "test"
Dynamic: author
Dynamic: author-email
Dynamic: classifier
Dynamic: description
Dynamic: description-content-type
Dynamic: home-page
Dynamic: keywords
Dynamic: license-file
Dynamic: provides-extra
Dynamic: requires-dist
Dynamic: summary
